lovelypancake/__init__.py
lovelypancake/calculate.py
lovelypancake/math_operations.py
lovelypancake/string_operations.py
lovely_pancake-1.0.6.dist-info/LICENSE
lovely_pancake-1.0.6.dist-info/METADATA
lovely_pancake-1.0.6.dist-info/WHEEL
lovely_pancake-1.0.6.dist-info/top_level.txt
lovely_pancake-1.0.6.dist-info/RECORD
