Metadata-Version: 2.1
Name: lovely-pancake
Version: 1.0.6
Summary: My lovely python package
Author: Ahmet Duzduran
License-File: LICENSE
